<?xml version="1.0" encoding="UTF-8" ?>
<class name="Loot" inherits="Resource" xmlns:xsi="http://www.w3.org/2001/XMLSchema-instance" xsi:noNamespaceSchemaLocation="https://raw.githubusercontent.com/godotengine/godot/master/doc/class.xsd">
	<brief_description>
		Resource containing a weighted list of loot items for random generation.
	</brief_description>
	<description>
		The Loot resource represents a loot table containing a weighted list of [LootItem] resources. It provides functionality for weighted random selection of items, commonly used in survival games for treasure chests, enemy drops, and resource gathering. Items with higher weights are more likely to be selected during random generation.
		
		The loot system supports configurable rolls functionality, inspired by Minecraft-style loot tables. You can set minimum and maximum roll counts to generate multiple items in a single loot generation call. For example, setting min_rolls=2 and max_rolls=4 will generate between 2-4 items each time the loot table is used.
		
		The total weight is calculated automatically from all contained loot items, and the random selection uses this total to ensure proper probability distribution.
	</description>
	<tutorials>
	</tutorials>
	<methods>
		<method name="get_random_items" qualifiers="const">
			<return type="LootItem[]" />
			<param index="0" name="rolls" type="int" default="-1" />
			<description>
				Returns an array of randomly selected [LootItem] resources. When [param rolls] is -1 (default), uses the configured roll range (min_rolls to max_rolls) with a random number of rolls within that range. When [param rolls] is a positive number, uses that exact number of rolls, overriding the configured range. Each roll is an independent weighted selection from the loot table. Returns an empty array if no valid items can be generated.
			</description>
		</method>
		<method name="get_total_weight" qualifiers="const">
			<return type="float" />
			<description>
				Calculates and returns the total weight of all [LootItem] resources in this loot table. This is used internally for weighted random selection calculations.
			</description>
		</method>
	</methods>
	<members>
		<member name="items" type="LootItem[]" setter="set_items" getter="get_items" default="[]">
			Array of [LootItem] resources that define what items can be generated and their relative probabilities. Each loot item contains an item ID, weight for probability calculation, and minimum/maximum amount ranges.
		</member>
		<member name="max_rolls" type="int" setter="set_max_rolls" getter="get_max_rolls" default="1">
			Maximum number of rolls when generating random items. Combined with min_rolls to define a range for random roll count generation. Must be greater than or equal to min_rolls. For fixed roll counts, set this equal to min_rolls.
		</member>
		<member name="min_rolls" type="int" setter="set_min_rolls" getter="get_min_rolls" default="1">
			Minimum number of rolls when generating random items. Combined with max_rolls to define a range for random roll count generation. Must be at least 1. For fixed roll counts, set this equal to max_rolls.
		</member>
		<member name="name" type="String" setter="set_name" getter="get_name" default="&quot;&quot;">
			Optional name for this loot table, useful for identification and organization in the inventory database.
		</member>
	</members>
</class>